imaris_convert/ImarisWriterCtypes.py
imaris_convert/PyImarisWriter.py
imaris_convert/__init__.py
imaris_convert/bpImarisWriter96.dll
imaris_convert/hdf5.dll
imaris_convert/imaris_convert.py
imaris_convert/zlib.dll
imaris_convert-1.0.1.dist-info/METADATA
imaris_convert-1.0.1.dist-info/WHEEL
imaris_convert-1.0.1.dist-info/entry_points.txt
imaris_convert-1.0.1.dist-info/top_level.txt
imaris_convert-1.0.1.dist-info/RECORD
